langchain_llm7/__init__.py
langchain_llm7/chat_llm7.py
langchain_llm7-2025.9.131316.dist-info/licenses/LICENSE
tests/__init__.py
tests/test_chat_llm7.py
langchain_llm7-2025.9.131316.dist-info/METADATA
langchain_llm7-2025.9.131316.dist-info/WHEEL
langchain_llm7-2025.9.131316.dist-info/top_level.txt
langchain_llm7-2025.9.131316.dist-info/RECORD
