Metadata-Version: 2.4
Name: langchain-llm7
Version: 2025.9.131316
Summary: A LangChain wrapper for LLM7 API
Home-page: https://github.com/chigwell/langchain_llm7
Author: Eugene Evstafev
Author-email: chigwel@gmail.com
License: Apache-2.0
Classifier: License :: OSI Approved :: Apache Software License
Classifier: Development Status :: 3 - Alpha
Classifier: Intended Audience :: Developers
Classifier: Programming Language :: Python :: 3
Classifier: Operating System :: OS Independent
Requires-Python: >=3.10
License-File: LICENSE
Requires-Dist: tokeniser>=0.0.3
Requires-Dist: requests==2.32.3
Requires-Dist: pydantic==2.11.3
Requires-Dist: langchain-core==0.3.51
Dynamic: author
Dynamic: author-email
Dynamic: classifier
Dynamic: description
Dynamic: description-content-type
Dynamic: home-page
Dynamic: license
Dynamic: license-file
Dynamic: requires-dist
Dynamic: requires-python
Dynamic: summary
